alidistlint/__init__.py
alidistlint/__main__.py
alidistlint/_version.py
alidistlint/common.py
alidistlint/git.py
alidistlint/headerlint.py
alidistlint/run.py
alidistlint/scriptlint.py
alidistlint/shellcheck.py
alidistlint/yamllint.py
alidistlint-1.7.5.dist-info/licenses/LICENSE
alidistlint-1.7.5.dist-info/METADATA
alidistlint-1.7.5.dist-info/WHEEL
alidistlint-1.7.5.dist-info/entry_points.txt
alidistlint-1.7.5.dist-info/top_level.txt
alidistlint-1.7.5.dist-info/RECORD
