Metadata-Version: 2.4
Name: alidistlint
Version: 1.7.5
Summary: A code linter for alidist packages
Author-email: Timo Wilken <timo.wilken@cern.ch>
Project-URL: Homepage, https://github.com/alisw/alidistlint
Classifier: Programming Language :: Python :: 3
Classifier: License :: OSI Approved :: GNU General Public License v3 (GPLv3)
Classifier: Operating System :: OS Independent
Classifier: Environment :: Console
Classifier: Intended Audience :: Developers
Classifier: Topic :: Software Development :: Quality Assurance
Requires-Python: >=3.9
License-File: LICENSE
Requires-Dist: cerberus
Requires-Dist: pyyaml
Provides-Extra: git
Requires-Dist: pygit2; extra == "git"
Provides-Extra: linters
Requires-Dist: yamllint; extra == "linters"
Dynamic: license-file
